{
  "main": {
    "id": "f2c1900518e61799",
    "type": "split",
    "children": [
      {
        "id": "b920f510c47f2f1b",
        "type": "tabs",
        "children": [
          {
            "id": "6b4d9d69e0150b8a",
            "type": "leaf",
            "state": {
              "type": "markdown",
              "state": {
                "file": "Notas/01 Linux/Linux.md",
                "mode": "source",
                "source": false,
                "backlinks": true,
                "backlinkOpts": {
                  "collapseAll": false,
                  "extraContext": false,
                  "sortOrder": "alphabetical",
                  "showSearch": false,
                  "searchQuery": "",
                  "backlinkCollapsed": false,
                  "unlinkedCollapsed": true
                }
              },
              "icon": "lucide-file",
              "title": "Linux"
            }
          },
          {
            "id": "5c96a70ace3e8000",
            "type": "leaf",
            "state": {
              "type": "markdown",
              "state": {
                "file": "Familias de Distribuciones Linux.md",
                "mode": "source",
                "source": false,
                "backlinks": true,
                "backlinkOpts": {
                  "collapseAll": false,
                  "extraContext": false,
                  "sortOrder": "alphabetical",
                  "showSearch": false,
                  "searchQuery": "",
                  "backlinkCollapsed": false,
                  "unlinkedCollapsed": true
                }
              },
              "icon": "lucide-file",
              "title": "Familias de Distribuciones Linux"
            }
          }
        ],
        "currentTab": 1
      }
    ],
    "direction": "vertical"
  },
  "left": {
    "id": "d968516a008d0b3f",
    "type": "split",
    "children": [
      {
        "id": "b9ab4a6d2335ce9d",
        "type": "tabs",
        "children": [
          {
            "id": "60a09ba8f2d0b296",
            "type": "leaf",
            "state": {
              "type": "search",
              "state": {
                "query": "",
                "matchingCase": true,
                "explainSearch": true,
                "collapseAll": true,
                "extraContext": true,
                "sortOrder": "alphabetical"
              },
              "icon": "lucide-search",
              "title": "Buscar"
            }
          },
          {
            "id": "4d0a035790bdae6f",
            "type": "leaf",
            "state": {
              "type": "bookmarks",
              "state": {},
              "icon": "lucide-bookmark",
              "title": "Marcadores"
            }
          },
          {
            "id": "21a970157e473559",
            "type": "leaf",
            "state": {
              "type": "file-explorer",
              "state": {
                "sortOrder": "alphabetical",
                "autoReveal": false
              },
              "icon": "lucide-folder-closed",
              "title": "Explorador de archivos"
            }
          }
        ],
        "currentTab": 2
      }
    ],
    "direction": "horizontal",
    "width": 323.5
  },
  "right": {
    "id": "d8225b93b61ce83c",
    "type": "split",
    "children": [
      {
        "id": "ad830ef6abe7f8d3",
        "type": "tabs",
        "children": [
          {
            "id": "d8f94e6b3ecb6cdf",
            "type": "leaf",
            "state": {
              "type": "backlink",
              "state": {
                "collapseAll": false,
                "extraContext": false,
                "sortOrder": "alphabetical",
                "showSearch": false,
                "searchQuery": "",
                "backlinkCollapsed": false,
                "unlinkedCollapsed": true
              },
              "icon": "links-coming-in",
              "title": "Enlaces entrantes"
            }
          },
          {
            "id": "705ef7687ee65164",
            "type": "leaf",
            "state": {
              "type": "outgoing-link",
              "state": {
                "file": "01_Rutas/01_Linux/Lección 1.md",
                "linksCollapsed": true,
                "unlinkedCollapsed": true
              },
              "icon": "links-going-out",
              "title": "Enlaces salientes de Lección 1"
            }
          },
          {
            "id": "44fcdf280811ead8",
            "type": "leaf",
            "state": {
              "type": "tag",
              "state": {
                "sortOrder": "frequency",
                "useHierarchy": true,
                "showSearch": false,
                "searchQuery": ""
              },
              "icon": "lucide-tags",
              "title": "Etiquetas"
            }
          },
          {
            "id": "80c385198ef22ddf",
            "type": "leaf",
            "state": {
              "type": "all-properties",
              "state": {
                "sortOrder": "frequency",
                "showSearch": false,
                "searchQuery": ""
              },
              "icon": "lucide-archive",
              "title": "Todas las propiedades"
            }
          },
          {
            "id": "a2e54b7db5bb8ff7",
            "type": "leaf",
            "state": {
              "type": "markdown",
              "state": {
                "file": "01_Rutas/01_Linux/Semana 1 — Fundamentos de Linux.md",
                "mode": "source",
                "source": false
              },
              "icon": "lucide-file",
              "title": "Semana 1 — Fundamentos de Linux"
            }
          },
          {
            "id": "6bf3d79ac89e28ee",
            "type": "leaf",
            "state": {
              "type": "outline",
              "state": {
                "followCursor": false,
                "showSearch": false,
                "searchQuery": ""
              },
              "icon": "lucide-list",
              "title": "Esquema"
            }
          },
          {
            "id": "906b74366e5b5af1",
            "type": "leaf",
            "state": {
              "type": "footnotes",
              "state": {},
              "icon": "lucide-file-signature",
              "title": "Notas al pie"
            }
          }
        ],
        "currentTab": 5
      }
    ],
    "direction": "horizontal",
    "width": 439.5,
    "collapsed": true
  },
  "left-ribbon": {
    "hiddenItems": {
      "switcher:Abrir selector rápido": false,
      "graph:Abrir vista gráfica": false,
      "canvas:Crear nuevo lienzo": false,
      "daily-notes:Abrir la nota de hoy": false,
      "templates:Insertar plantilla": false,
      "command-palette:Abrir paleta de comandos": false,
      "bases:Crear nueva base": false,
      "zk-prefixer:Crear nueva nota única": false,
      "workspaces:Gestionar disposiciones de espacio de trabajo": false,
      "random-note:Abrir nota al azar": false,
      "publish:Publicar cambios": false
    }
  },
  "active": "5c96a70ace3e8000",
  "lastOpenFiles": [
    "Notas/01 Linux/Mapa Linux.md",
    "Buenas_practicas_en_Linux.md",
    "Errores_comunes_en_WSL.md",
    "Notas/01 Linux/Linux.md",
    "Kernel de Linux.md",
    "Qué es una distribución Linux.md",
    "Filosofía del Software Libre.md",
    "Notas/01 Linux/Paquetes esenciales por distros.md",
    "Familias de Distribuciones Linux.md",
    "Notas/01 Linux/Instalación y Primer uso de Linux.md",
    "Notas/00 Orientacion/🌐 Mapa de mi aprendizaje.md",
    "Historia de GNU Linux.md",
    "Notas/01 Linux/Instalación Linux en WSL.md",
    "Qué es GNU Linux.md",
    "Notas/00 Orientacion/Metas.md",
    "Notas/02 Bash/Mapa Bash.md",
    "Notas/01 Linux/rolling release.md",
    "Notas/01 Linux/SSH y GitHub.md",
    "Paquetes_esenciales_por_distro.md",
    "Notas/01 Linux/Bash vs Zsh y personalización.md",
    "Why-Python-Heres-Why-980x551.webp",
    "Notas/01 Linux/Alias básicos en Bash.md",
    "Notas/01 Linux/Actualización sistema en Linux.md",
    "Notas/01 Linux/Usuarios y sudo en Linux.md",
    "Notas/01 Linux/Instalación Linux en Termux con proot-distro.md",
    "Notas/01 Linux/WSL vs proot-distros.md",
    "Notas/04 Matematicas/Título claro del tema 1.md",
    "Notas/FB_IMG_1769723860184.jpg",
    "Notas/04 Matematicas",
    "Notas",
    "Notas/03 Python",
    "Notas/02 Bash/03 Patrones",
    "Notas/02 Bash/02 Scripting",
    "Notas/02 Bash/01 Referencia",
    "Notas/01 Linux/05 Herramientas",
    "Notas/01 Linux/04 Administración",
    "Notas/01 Linux/03 Distros y modelos",
    "Notas/01 Linux/01 Conceptos"
  ]
}